mcp_schema_validator/__init__.py
mcp_schema_validator/main.py
mcp_schema_validator-0.1.0.dist-info/METADATA
mcp_schema_validator-0.1.0.dist-info/WHEEL
mcp_schema_validator-0.1.0.dist-info/top_level.txt
mcp_schema_validator-0.1.0.dist-info/RECORD
